{"name":"@tarojs/webpack-runner","versions":[{"reproduced":false,"score":null,"timestamp":"2026-01-18T12:31:55.570Z","version":"1.0.0-beta.22"},{"reproduced":false,"score":null,"timestamp":"2026-01-18T12:31:49.329Z","version":"1.0.0-beta.21"},{"reproduced":false,"score":null,"timestamp":"2026-01-18T12:30:48.380Z","version":"1.0.0-beta.20"},{"reproduced":false,"score":null,"timestamp":"2026-01-18T12:30:21.496Z","version":"1.0.0-beta.19"},{"reproduced":false,"score":null,"timestamp":"2026-01-18T12:30:01.876Z","version":"1.0.0-beta.18"},{"reproduced":false,"score":null,"timestamp":"2026-01-18T12:29:53.830Z","version":"1.0.0-beta.17"},{"reproduced":false,"score":null,"timestamp":"2026-01-18T12:29:45.588Z","version":"1.0.0-beta.16"},{"reproduced":false,"score":null,"timestamp":"2026-01-18T12:30:43.586Z","version":"1.0.0-beta.15"},{"reproduced":false,"score":null,"timestamp":"2026-01-18T12:29:00.738Z","version":"1.0.0-beta.14"},{"reproduced":false,"score":null,"timestamp":"2026-01-18T12:28:16.975Z","version":"1.0.0-beta.13"},{"reproduced":false,"score":null,"timestamp":"2026-01-18T12:27:26.436Z","version":"1.0.0-beta.12"},{"reproduced":false,"score":null,"timestamp":"2026-01-18T12:27:15.212Z","version":"1.0.0-beta.11"},{"reproduced":false,"score":null,"timestamp":"2026-01-18T12:26:45.182Z","version":"1.0.0-beta.10"},{"reproduced":false,"score":null,"timestamp":"2026-01-18T12:26:32.792Z","version":"1.0.0-beta.9"},{"reproduced":false,"score":null,"timestamp":"2026-01-18T12:27:28.772Z","version":"1.0.0-beta.8"},{"reproduced":false,"score":null,"timestamp":"2026-01-18T12:27:13.901Z","version":"1.0.0-beta.7"},{"reproduced":false,"score":null,"timestamp":"2026-01-18T12:26:34.179Z","version":"1.0.0-beta.6"},{"reproduced":false,"score":null,"timestamp":"2026-01-18T12:26:23.257Z","version":"1.0.0-beta.5"},{"reproduced":false,"score":null,"timestamp":"2026-01-18T12:24:59.491Z","version":"1.0.0-beta.4"},{"reproduced":false,"score":null,"timestamp":"2026-01-18T12:20:16.863Z","version":"1.0.0-beta.3"},{"reproduced":false,"score":null,"timestamp":"2026-01-18T11:40:49.013Z","version":"1.0.0-beta.2"},{"reproduced":false,"score":null,"timestamp":"2026-01-18T11:40:41.272Z","version":"1.0.0-beta.1"},{"reproduced":false,"score":null,"timestamp":"2026-01-18T11:40:34.874Z","version":"1.0.0-beta.0"},{"reproduced":false,"score":null,"timestamp":"2026-01-18T11:39:29.169Z","version":"0.0.73"},{"reproduced":false,"score":null,"timestamp":"2026-01-18T11:39:24.126Z","version":"0.0.72"},{"reproduced":false,"score":null,"timestamp":"2026-01-18T11:39:14.823Z","version":"0.0.71"},{"reproduced":false,"score":null,"timestamp":"2026-01-18T11:38:48.594Z","version":"0.0.70"},{"reproduced":false,"score":null,"timestamp":"2026-01-18T11:38:20.700Z","version":"0.0.69-beta.1"},{"reproduced":false,"score":null,"timestamp":"2026-01-18T11:38:23.610Z","version":"0.0.69"},{"reproduced":false,"score":null,"timestamp":"2026-01-18T11:37:42.554Z","version":"0.0.68-beta.4"},{"reproduced":false,"score":null,"timestamp":"2026-01-18T11:37:12.748Z","version":"0.0.68-beta.3"},{"reproduced":false,"score":null,"timestamp":"2026-01-18T11:37:11.072Z","version":"0.0.68-beta.1"},{"reproduced":false,"score":null,"timestamp":"2026-01-18T11:37:35.371Z","version":"0.0.68"},{"reproduced":false,"score":null,"timestamp":"2026-01-18T11:37:01.954Z","version":"0.0.67"},{"reproduced":false,"score":null,"timestamp":"2026-01-18T11:36:58.434Z","version":"0.0.66"},{"reproduced":false,"score":null,"timestamp":"2026-01-18T11:36:06.086Z","version":"0.0.65"},{"reproduced":false,"score":null,"timestamp":"2026-01-18T11:35:24.819Z","version":"0.0.64"},{"reproduced":false,"score":null,"timestamp":"2026-01-18T11:35:02.851Z","version":"0.0.63"},{"reproduced":false,"score":null,"timestamp":"2026-01-18T11:35:00.117Z","version":"0.0.62"},{"reproduced":false,"score":null,"timestamp":"2026-01-18T11:31:36.298Z","version":"0.0.61"},{"reproduced":false,"score":null,"timestamp":"2026-01-18T10:43:57.691Z","version":"0.0.60"},{"reproduced":false,"score":null,"timestamp":"2026-01-18T10:41:55.617Z","version":"0.0.59"},{"reproduced":false,"score":null,"timestamp":"2026-01-18T10:41:21.080Z","version":"0.0.58"},{"reproduced":false,"score":null,"timestamp":"2026-01-18T10:40:55.117Z","version":"0.0.57"},{"reproduced":false,"score":null,"timestamp":"2026-01-18T10:40:29.701Z","version":"0.0.56"},{"reproduced":false,"score":null,"timestamp":"2026-01-18T10:40:14.543Z","version":"0.0.55"},{"reproduced":false,"score":null,"timestamp":"2026-01-18T10:40:10.631Z","version":"0.0.54"},{"reproduced":false,"score":null,"timestamp":"2026-01-18T10:40:13.971Z","version":"0.0.53"},{"reproduced":false,"score":null,"timestamp":"2026-01-18T10:39:32.472Z","version":"0.0.52"},{"reproduced":false,"score":null,"timestamp":"2026-01-18T10:39:24.187Z","version":"0.0.51"},{"reproduced":false,"score":null,"timestamp":"2026-01-18T10:39:58.178Z","version":"0.0.50"},{"reproduced":false,"score":null,"timestamp":"2026-01-18T10:38:53.448Z","version":"0.0.49"},{"reproduced":false,"score":null,"timestamp":"2026-01-18T10:38:15.975Z","version":"0.0.47"},{"reproduced":false,"score":null,"timestamp":"2026-01-18T10:38:12.396Z","version":"0.0.46"},{"reproduced":false,"score":null,"timestamp":"2026-01-18T10:38:01.626Z","version":"0.0.45"},{"reproduced":false,"score":null,"timestamp":"2026-01-18T10:37:42.910Z","version":"0.0.44-beta.4"},{"reproduced":false,"score":null,"timestamp":"2026-01-18T10:36:01.262Z","version":"0.0.44-beta.3"},{"reproduced":false,"score":null,"timestamp":"2026-01-18T10:35:57.699Z","version":"0.0.44-beta.2"},{"reproduced":false,"score":null,"timestamp":"2026-01-18T10:35:49.603Z","version":"0.0.44-beta.1"},{"reproduced":false,"score":null,"timestamp":"2026-01-18T10:37:48.994Z","version":"0.0.44"},{"reproduced":false,"score":null,"timestamp":"2026-01-18T09:41:17.611Z","version":"0.0.42"},{"reproduced":false,"score":null,"timestamp":"2026-01-18T09:39:23.329Z","version":"0.0.41"},{"reproduced":false,"score":null,"timestamp":"2026-01-18T09:39:17.540Z","version":"0.0.40"},{"reproduced":false,"score":null,"timestamp":"2026-01-18T09:40:08.986Z","version":"0.0.39"},{"reproduced":false,"score":null,"timestamp":"2026-01-18T09:38:55.678Z","version":"0.0.38"},{"reproduced":false,"score":null,"timestamp":"2026-01-18T09:38:39.900Z","version":"0.0.37"},{"reproduced":false,"score":null,"timestamp":"2026-01-18T09:38:38.116Z","version":"0.0.36"},{"reproduced":false,"score":null,"timestamp":"2026-01-18T09:38:19.260Z","version":"0.0.35"},{"reproduced":false,"score":null,"timestamp":"2026-01-18T09:38:14.397Z","version":"0.0.34"},{"reproduced":false,"score":null,"timestamp":"2026-01-18T09:37:52.623Z","version":"0.0.32"},{"reproduced":false,"score":null,"timestamp":"2026-01-18T09:37:53.225Z","version":"0.0.31"},{"reproduced":false,"score":null,"timestamp":"2026-01-18T09:37:28.346Z","version":"0.0.30"},{"reproduced":false,"score":null,"timestamp":"2026-01-18T09:36:36.864Z","version":"0.0.29"},{"reproduced":false,"score":null,"timestamp":"2026-01-18T09:36:16.373Z","version":"0.0.28"},{"reproduced":false,"score":null,"timestamp":"2026-01-18T09:35:56.976Z","version":"0.0.27"},{"reproduced":false,"score":null,"timestamp":"2026-01-18T09:35:55.913Z","version":"0.0.26"},{"reproduced":false,"score":null,"timestamp":"2026-01-18T09:35:53.662Z","version":"0.0.25"},{"reproduced":false,"score":null,"timestamp":"2026-01-18T09:35:55.129Z","version":"0.0.24"},{"reproduced":false,"score":null,"timestamp":"2026-01-18T09:35:29.061Z","version":"0.0.23"},{"reproduced":false,"score":null,"timestamp":"2026-01-18T09:34:26.199Z","version":"0.0.22"},{"reproduced":false,"score":null,"timestamp":"2026-01-18T08:32:10.631Z","version":"0.0.21"},{"reproduced":false,"score":null,"timestamp":"2026-01-18T08:30:31.113Z","version":"0.0.20"},{"reproduced":false,"score":null,"timestamp":"2026-01-18T08:31:44.367Z","version":"0.0.19"},{"reproduced":false,"score":null,"timestamp":"2026-01-18T08:28:55.325Z","version":"0.0.18"},{"reproduced":false,"score":null,"timestamp":"2026-01-18T08:31:58.810Z","version":"0.0.17"},{"reproduced":false,"score":null,"timestamp":"2026-01-18T08:33:02.900Z","version":"0.0.16"},{"reproduced":false,"score":null,"timestamp":"2026-01-18T08:34:11.772Z","version":"0.0.15"},{"reproduced":false,"score":null,"timestamp":"2026-01-18T08:32:00.920Z","version":"0.0.14"},{"reproduced":false,"score":null,"timestamp":"2026-01-18T08:28:40.979Z","version":"0.0.13"},{"reproduced":false,"score":null,"timestamp":"2026-01-18T08:31:26.634Z","version":"0.0.12"},{"reproduced":false,"score":null,"timestamp":"2026-01-18T08:33:12.454Z","version":"0.0.11"},{"reproduced":false,"score":null,"timestamp":"2026-01-18T08:29:42.713Z","version":"0.0.10"},{"reproduced":false,"score":null,"timestamp":"2026-01-18T08:31:21.292Z","version":"0.0.9"},{"reproduced":false,"score":null,"timestamp":"2026-01-18T08:31:49.555Z","version":"0.0.8"},{"reproduced":false,"score":null,"timestamp":"2026-01-18T08:30:34.487Z","version":"0.0.7"},{"reproduced":false,"score":null,"timestamp":"2026-01-18T08:29:00.454Z","version":"0.0.6"},{"reproduced":false,"score":null,"timestamp":"2026-01-18T08:30:57.312Z","version":"0.0.5"},{"reproduced":false,"score":null,"timestamp":"2026-01-18T08:28:43.842Z","version":"0.0.4"},{"reproduced":false,"score":null,"timestamp":"2026-01-18T08:30:15.577Z","version":"0.0.3"},{"reproduced":false,"score":null,"timestamp":"2026-01-18T08:30:14.330Z","version":"0.0.2"}]}