{"name":"chrome-launcher","versions":[{"reproduced":false,"score":0.5,"timestamp":"2026-01-11T17:23:03.070Z","version":"1.2.1"},{"reproduced":false,"score":0.5714285714285714,"timestamp":"2026-01-11T17:22:46.743Z","version":"1.2.0"},{"reproduced":false,"score":0.5714285714285714,"timestamp":"2026-01-11T17:22:29.453Z","version":"1.1.2"},{"reproduced":false,"score":0.5714285714285714,"timestamp":"2026-01-11T17:22:17.263Z","version":"1.1.1"},{"reproduced":false,"score":0.5714285714285714,"timestamp":"2026-01-11T16:59:25.498Z","version":"1.1.0"},{"reproduced":false,"score":0.5714285714285714,"timestamp":"2026-01-11T16:53:05.232Z","version":"1.0.0"},{"reproduced":false,"score":0.5714285714285714,"timestamp":"2026-01-11T16:52:57.825Z","version":"0.15.2"},{"reproduced":false,"score":0.3409090909090909,"timestamp":"2026-01-11T16:52:58.517Z","version":"0.15.1"},{"reproduced":false,"score":0.5384615384615384,"timestamp":"2026-01-11T16:52:52.647Z","version":"0.15.0"},{"reproduced":false,"score":0.52,"timestamp":"2026-01-11T16:53:36.503Z","version":"0.14.2"},{"reproduced":false,"score":0.52,"timestamp":"2026-01-11T16:52:46.320Z","version":"0.14.1"},{"reproduced":false,"score":0.52,"timestamp":"2026-01-11T16:52:32.113Z","version":"0.14.0"},{"reproduced":false,"score":0.48,"timestamp":"2026-01-11T16:52:00.746Z","version":"0.13.4"},{"reproduced":false,"score":0.3157894736842105,"timestamp":"2026-01-11T16:51:51.032Z","version":"0.13.3"},{"reproduced":false,"score":0.3157894736842105,"timestamp":"2026-01-11T16:51:33.837Z","version":"0.13.2"},{"reproduced":false,"score":0.3157894736842105,"timestamp":"2026-01-11T16:51:32.900Z","version":"0.13.1"},{"reproduced":false,"score":0.3157894736842105,"timestamp":"2026-01-11T16:52:15.393Z","version":"0.13.0"},{"reproduced":false,"score":0.3076923076923077,"timestamp":"2026-01-11T16:51:19.177Z","version":"0.12.0"},{"reproduced":false,"score":0.48,"timestamp":"2026-01-11T16:51:51.062Z","version":"0.11.2"},{"reproduced":false,"score":0.3076923076923077,"timestamp":"2026-01-11T16:51:01.857Z","version":"0.11.1"},{"reproduced":false,"score":0.3076923076923077,"timestamp":"2026-01-11T16:50:31.571Z","version":"0.11.0"},{"reproduced":false,"score":0.5,"timestamp":"2026-01-11T16:50:30.301Z","version":"0.10.7"},{"reproduced":false,"score":1,"timestamp":"2026-01-11T16:49:54.711Z","version":"0.10.6"},{"reproduced":false,"score":0.3076923076923077,"timestamp":"2026-01-11T16:49:29.591Z","version":"0.10.5"},{"reproduced":false,"score":0.3076923076923077,"timestamp":"2026-01-11T16:16:56.410Z","version":"0.10.4"},{"reproduced":false,"score":0.48,"timestamp":"2026-01-11T16:17:25.158Z","version":"0.10.2"},{"reproduced":false,"score":0.48,"timestamp":"2026-01-11T16:17:59.920Z","version":"0.10.1"},{"reproduced":false,"score":0.4583333333333333,"timestamp":"2026-01-11T16:18:55.024Z","version":"0.10.0"},{"reproduced":false,"score":0.4166666666666667,"timestamp":"2026-01-11T16:18:00.825Z","version":"0.8.1"},{"reproduced":false,"score":0.4166666666666667,"timestamp":"2026-01-11T16:19:23.254Z","version":"0.8.0"},{"reproduced":false,"score":0.4166666666666667,"timestamp":"2026-01-11T16:16:54.372Z","version":"0.7.0"}]}