{"name":"egg-mock","versions":[{"reproduced":true,"score":1,"timestamp":"2026-01-04T13:24:37.270Z","version":"6.0.0-beta.2"},{"reproduced":false,"score":0.9714285714285714,"timestamp":"2026-01-04T13:24:05.093Z","version":"6.0.0-beta.1"},{"reproduced":false,"score":0.8,"timestamp":"2026-01-04T13:23:47.205Z","version":"6.0.0-beta.0"},{"reproduced":true,"score":1,"timestamp":"2026-01-04T13:24:44.607Z","version":"5.15.2"},{"reproduced":true,"score":1,"timestamp":"2026-01-04T13:23:37.879Z","version":"5.15.1"},{"reproduced":true,"score":1,"timestamp":"2026-01-04T13:23:46.697Z","version":"5.15.0"},{"reproduced":true,"score":1,"timestamp":"2026-01-04T13:23:24.360Z","version":"5.14.0"},{"reproduced":true,"score":1,"timestamp":"2026-01-04T13:23:33.726Z","version":"5.13.0"},{"reproduced":true,"score":1,"timestamp":"2026-01-04T13:23:26.048Z","version":"5.12.5"},{"reproduced":true,"score":1,"timestamp":"2026-01-04T13:23:04.275Z","version":"5.12.4"},{"reproduced":true,"score":1,"timestamp":"2026-01-04T13:22:18.756Z","version":"5.12.3"},{"reproduced":true,"score":1,"timestamp":"2026-01-04T13:22:02.410Z","version":"5.12.2"},{"reproduced":true,"score":1,"timestamp":"2026-01-04T13:21:35.482Z","version":"5.12.1"},{"reproduced":true,"score":1,"timestamp":"2026-01-04T13:21:20.779Z","version":"5.12.0"},{"reproduced":true,"score":1,"timestamp":"2026-01-04T13:21:10.028Z","version":"5.11.0"},{"reproduced":true,"score":1,"timestamp":"2026-01-04T13:21:03.568Z","version":"5.10.9"},{"reproduced":false,"score":1,"timestamp":"2026-01-04T13:20:56.037Z","version":"5.10.8"},{"reproduced":false,"score":1,"timestamp":"2026-01-04T13:20:50.490Z","version":"5.10.7"},{"reproduced":false,"score":1,"timestamp":"2026-01-04T13:20:49.165Z","version":"5.10.6"},{"reproduced":true,"score":1,"timestamp":"2026-01-04T13:20:35.085Z","version":"5.10.5"},{"reproduced":true,"score":1,"timestamp":"2026-01-04T13:19:37.026Z","version":"5.10.4"},{"reproduced":true,"score":1,"timestamp":"2026-01-04T13:19:19.872Z","version":"5.10.3"},{"reproduced":true,"score":1,"timestamp":"2026-01-04T13:19:07.080Z","version":"5.10.2"},{"reproduced":true,"score":1,"timestamp":"2026-01-04T13:18:53.196Z","version":"5.10.1"},{"reproduced":true,"score":1,"timestamp":"2026-01-04T13:18:39.596Z","version":"5.10.0"},{"reproduced":true,"score":1,"timestamp":"2026-01-04T13:18:32.360Z","version":"5.9.4"},{"reproduced":true,"score":1,"timestamp":"2026-01-04T13:18:33.068Z","version":"5.9.3"},{"reproduced":true,"score":1,"timestamp":"2026-01-04T13:18:23.520Z","version":"5.9.2"},{"reproduced":true,"score":1,"timestamp":"2026-01-04T13:18:23.248Z","version":"5.9.1"},{"reproduced":true,"score":1,"timestamp":"2026-01-04T13:17:56.329Z","version":"5.9.0"},{"reproduced":true,"score":1,"timestamp":"2026-01-04T13:17:00.158Z","version":"5.8.4"},{"reproduced":true,"score":1,"timestamp":"2026-01-04T13:16:42.776Z","version":"5.8.3"},{"reproduced":false,"score":0.9393939393939394,"timestamp":"2026-01-04T13:16:43.661Z","version":"5.8.2-beta.8"},{"reproduced":true,"score":1,"timestamp":"2026-01-04T13:16:16.853Z","version":"5.8.2-beta.7"},{"reproduced":false,"score":0.9696969696969697,"timestamp":"2026-01-04T13:16:17.077Z","version":"5.8.2-beta.6"},{"reproduced":true,"score":1,"timestamp":"2026-01-04T13:16:10.977Z","version":"5.8.2-beta.5"},{"reproduced":false,"score":0.9696969696969697,"timestamp":"2026-01-04T13:16:08.052Z","version":"5.8.2-beta.4"},{"reproduced":false,"score":0.8484848484848485,"timestamp":"2026-01-04T13:16:00.920Z","version":"5.8.2-beta.3"},{"reproduced":false,"score":0.8484848484848485,"timestamp":"2026-01-04T13:15:42.842Z","version":"5.8.2-beta.2"},{"reproduced":false,"score":0.8484848484848485,"timestamp":"2026-01-04T13:15:28.737Z","version":"5.8.2-beta.1"},{"reproduced":false,"score":0.8484848484848485,"timestamp":"2026-01-04T13:14:35.239Z","version":"5.8.2-beta.0"},{"reproduced":true,"score":1,"timestamp":"2026-01-04T13:14:19.259Z","version":"5.8.2"},{"reproduced":true,"score":1,"timestamp":"2026-01-04T13:14:20.070Z","version":"5.8.1"},{"reproduced":true,"score":1,"timestamp":"2026-01-04T13:13:53.836Z","version":"5.8.0"},{"reproduced":true,"score":1,"timestamp":"2026-01-04T13:13:46.755Z","version":"5.7.1"},{"reproduced":true,"score":1,"timestamp":"2026-01-04T13:13:50.212Z","version":"5.7.0"},{"reproduced":true,"score":1,"timestamp":"2026-01-04T13:13:42.975Z","version":"5.6.0"},{"reproduced":true,"score":1,"timestamp":"2026-01-04T13:13:39.323Z","version":"5.5.0"},{"reproduced":false,"score":0.96875,"timestamp":"2026-01-04T13:13:12.830Z","version":"5.4.0"},{"reproduced":false,"score":0.96875,"timestamp":"2026-01-04T13:13:04.614Z","version":"5.3.0"},{"reproduced":false,"score":0.96875,"timestamp":"2026-01-04T13:12:09.715Z","version":"5.2.1"},{"reproduced":false,"score":0.96875,"timestamp":"2026-01-04T13:11:50.645Z","version":"5.2.0"},{"reproduced":false,"score":0.96875,"timestamp":"2026-01-04T13:11:52.514Z","version":"5.1.0"},{"reproduced":true,"score":1,"timestamp":"2026-01-04T13:11:30.730Z","version":"5.0.2"},{"reproduced":false,"score":0.9642857142857143,"timestamp":"2026-01-04T13:11:23.715Z","version":"5.0.1"},{"reproduced":false,"score":0.9642857142857143,"timestamp":"2026-01-04T13:11:21.909Z","version":"5.0.0"},{"reproduced":false,"score":0.9615384615384616,"timestamp":"2026-01-04T13:11:15.824Z","version":"4.2.1"},{"reproduced":false,"score":0.9615384615384616,"timestamp":"2026-01-04T13:11:10.267Z","version":"4.2.0"},{"reproduced":false,"score":0.9615384615384616,"timestamp":"2026-01-04T13:10:31.357Z","version":"4.1.0"},{"reproduced":false,"score":0.9615384615384616,"timestamp":"2026-01-04T13:09:30.797Z","version":"4.0.1"},{"reproduced":false,"score":0.9615384615384616,"timestamp":"2026-01-04T13:09:13.901Z","version":"4.0.0"},{"reproduced":false,"score":0.9615384615384616,"timestamp":"2026-01-04T13:10:41.795Z","version":"3.26.0"},{"reproduced":false,"score":0.9615384615384616,"timestamp":"2026-01-04T13:09:00.992Z","version":"3.25.1"},{"reproduced":false,"score":0.9615384615384616,"timestamp":"2026-01-04T13:08:51.723Z","version":"3.25.0"},{"reproduced":false,"score":0.9615384615384616,"timestamp":"2026-01-04T13:08:50.725Z","version":"3.24.2"},{"reproduced":false,"score":0.9615384615384616,"timestamp":"2026-01-04T13:08:42.754Z","version":"3.24.1"},{"reproduced":false,"score":0.9615384615384616,"timestamp":"2026-01-04T13:08:32.143Z","version":"3.24.0"},{"reproduced":false,"score":0.9615384615384616,"timestamp":"2026-01-04T13:08:31.276Z","version":"3.23.2"},{"reproduced":false,"score":0.9615384615384616,"timestamp":"2026-01-04T13:08:00.784Z","version":"3.23.1"},{"reproduced":false,"score":0.9615384615384616,"timestamp":"2026-01-04T13:07:55.066Z","version":"3.23.0"},{"reproduced":false,"score":0.9615384615384616,"timestamp":"2026-01-04T13:06:41.445Z","version":"3.22.4"},{"reproduced":false,"score":0.9615384615384616,"timestamp":"2026-01-04T13:06:35.405Z","version":"3.22.3"},{"reproduced":false,"score":0.9615384615384616,"timestamp":"2026-01-04T13:06:27.117Z","version":"3.22.2"},{"reproduced":false,"score":0.96,"timestamp":"2026-01-04T13:06:21.298Z","version":"3.22.1"},{"reproduced":false,"score":0.96,"timestamp":"2026-01-04T13:06:20.219Z","version":"3.22.0"},{"reproduced":false,"score":0.92,"timestamp":"2026-01-04T13:06:07.991Z","version":"3.21.0"},{"reproduced":false,"score":0.9583333333333334,"timestamp":"2026-01-04T13:06:01.230Z","version":"3.20.1"},{"reproduced":false,"score":0.9583333333333334,"timestamp":"2026-01-04T13:06:02.721Z","version":"3.20.0"},{"reproduced":false,"score":0.9545454545454546,"timestamp":"2026-01-04T13:05:28.438Z","version":"3.19.7"},{"reproduced":false,"score":0.9545454545454546,"timestamp":"2026-01-04T13:05:24.204Z","version":"3.19.6"},{"reproduced":false,"score":0.9545454545454546,"timestamp":"2026-01-04T13:04:04.821Z","version":"3.19.5"},{"reproduced":false,"score":0.9130434782608695,"timestamp":"2026-01-04T13:04:03.034Z","version":"3.19.4"},{"reproduced":false,"score":0.9545454545454546,"timestamp":"2026-01-04T13:03:51.953Z","version":"3.19.3"},{"reproduced":false,"score":0.9545454545454546,"timestamp":"2026-01-04T13:03:48.252Z","version":"3.19.2"},{"reproduced":false,"score":0.9545454545454546,"timestamp":"2026-01-04T13:03:48.474Z","version":"3.19.1"},{"reproduced":false,"score":0.9090909090909091,"timestamp":"2026-01-04T13:03:26.801Z","version":"3.19.0"},{"reproduced":false,"score":0.9523809523809523,"timestamp":"2026-01-04T13:03:32.519Z","version":"3.18.0"},{"reproduced":false,"score":0.9047619047619048,"timestamp":"2026-01-04T13:03:30.288Z","version":"3.17.3"},{"reproduced":false,"score":0.95,"timestamp":"2026-01-04T13:02:56.665Z","version":"3.17.2"},{"reproduced":false,"score":0.9047619047619048,"timestamp":"2026-01-04T13:02:48.563Z","version":"3.17.1"},{"reproduced":false,"score":0.9047619047619048,"timestamp":"2026-01-04T13:01:27.119Z","version":"3.17.0"},{"reproduced":false,"score":0.9047619047619048,"timestamp":"2026-01-04T13:01:29.120Z","version":"3.16.0"},{"reproduced":false,"score":0.95,"timestamp":"2026-01-04T13:01:08.149Z","version":"3.15.1"},{"reproduced":false,"score":0.95,"timestamp":"2026-01-04T13:01:13.895Z","version":"3.15.0"},{"reproduced":false,"score":0.9473684210526315,"timestamp":"2026-01-04T13:01:11.807Z","version":"3.14.1"},{"reproduced":false,"score":0.9473684210526315,"timestamp":"2026-01-04T13:01:01.411Z","version":"3.14.0"},{"reproduced":false,"score":0.9473684210526315,"timestamp":"2026-01-04T13:00:54.643Z","version":"3.13.1"},{"reproduced":false,"score":0.9473684210526315,"timestamp":"2026-01-04T13:00:54.418Z","version":"3.13.0"},{"reproduced":false,"score":0.8947368421052632,"timestamp":"2026-01-04T13:00:25.504Z","version":"3.12.2"},{"reproduced":false,"score":0.8947368421052632,"timestamp":"2026-01-04T13:00:19.254Z","version":"3.12.1"},{"reproduced":false,"score":0.8947368421052632,"timestamp":"2026-01-04T12:58:36.156Z","version":"3.12.0"},{"reproduced":false,"score":0.8947368421052632,"timestamp":"2026-01-04T12:58:42.968Z","version":"3.11.0"},{"reproduced":false,"score":0.8888888888888888,"timestamp":"2026-01-04T12:58:25.011Z","version":"3.10.0"},{"reproduced":false,"score":0.8888888888888888,"timestamp":"2026-01-04T12:58:28.266Z","version":"3.9.1"},{"reproduced":false,"score":0.8888888888888888,"timestamp":"2026-01-04T12:58:41.237Z","version":"3.9.0"},{"reproduced":false,"score":0.8823529411764706,"timestamp":"2026-01-04T12:58:29.202Z","version":"3.8.0"},{"reproduced":false,"score":0.8823529411764706,"timestamp":"2026-01-04T12:58:23.748Z","version":"3.7.2"},{"reproduced":false,"score":0.8823529411764706,"timestamp":"2026-01-04T12:58:35.971Z","version":"3.7.1"},{"reproduced":false,"score":0.8823529411764706,"timestamp":"2026-01-04T12:57:48.996Z","version":"3.7.0"},{"reproduced":false,"score":0.875,"timestamp":"2026-01-04T12:57:54.096Z","version":"3.6.1"},{"reproduced":false,"score":0.875,"timestamp":"2026-01-04T12:56:10.281Z","version":"3.6.0"},{"reproduced":false,"score":0.8333333333333334,"timestamp":"2026-01-04T12:55:58.654Z","version":"3.5.0"},{"reproduced":false,"score":0.8333333333333334,"timestamp":"2026-01-04T12:56:08.006Z","version":"3.4.0"},{"reproduced":false,"score":0.8333333333333334,"timestamp":"2026-01-04T12:55:50.998Z","version":"3.3.0"},{"reproduced":false,"score":0.8333333333333334,"timestamp":"2026-01-04T12:55:50.266Z","version":"3.2.0"},{"reproduced":false,"score":0.8333333333333334,"timestamp":"2026-01-04T12:55:57.719Z","version":"3.1.2"},{"reproduced":false,"score":0.8333333333333334,"timestamp":"2026-01-04T12:55:50.281Z","version":"3.1.1"},{"reproduced":false,"score":0.8181818181818182,"timestamp":"2026-01-04T12:55:46.504Z","version":"3.1.0"},{"reproduced":false,"score":0.8181818181818182,"timestamp":"2026-01-04T12:55:48.359Z","version":"3.0.1"},{"reproduced":false,"score":0.8181818181818182,"timestamp":"2026-01-04T12:55:44.471Z","version":"3.0.0"},{"reproduced":false,"score":0.8181818181818182,"timestamp":"2026-01-04T12:53:59.901Z","version":"2.4.0"},{"reproduced":false,"score":0.8181818181818182,"timestamp":"2026-01-04T12:53:56.044Z","version":"2.3.1"},{"reproduced":false,"score":0.8181818181818182,"timestamp":"2026-01-04T12:53:52.660Z","version":"2.3.0"},{"reproduced":false,"score":0.8181818181818182,"timestamp":"2026-01-04T12:53:47.643Z","version":"2.2.0"},{"reproduced":false,"score":0.8181818181818182,"timestamp":"2026-01-04T12:53:44.749Z","version":"2.1.0"},{"reproduced":false,"score":0.8181818181818182,"timestamp":"2026-01-04T12:53:44.710Z","version":"2.0.0"},{"reproduced":false,"score":0.8181818181818182,"timestamp":"2026-01-04T12:53:44.751Z","version":"1.3.1"},{"reproduced":false,"score":0.8181818181818182,"timestamp":"2026-01-04T12:53:46.417Z","version":"1.3.0"},{"reproduced":false,"score":0.8181818181818182,"timestamp":"2026-01-04T12:53:42.639Z","version":"1.2.1"},{"reproduced":false,"score":0.8181818181818182,"timestamp":"2026-01-04T12:53:42.848Z","version":"1.2.0"},{"reproduced":false,"score":0.8181818181818182,"timestamp":"2026-01-04T12:51:44.275Z","version":"1.1.0"},{"reproduced":false,"score":0.8181818181818182,"timestamp":"2026-01-04T12:51:45.670Z","version":"1.0.0"},{"reproduced":false,"score":0.9,"timestamp":"2026-01-04T12:51:44.197Z","version":"0.0.8"},{"reproduced":false,"score":0.9,"timestamp":"2026-01-04T12:51:43.454Z","version":"0.0.7"},{"reproduced":false,"score":0.9,"timestamp":"2026-01-04T12:51:49.819Z","version":"0.0.6"},{"reproduced":false,"score":0.9,"timestamp":"2026-01-04T12:51:44.294Z","version":"0.0.5"},{"reproduced":false,"score":0.9,"timestamp":"2026-01-04T12:51:45.034Z","version":"0.0.4"},{"reproduced":false,"score":1,"timestamp":"2026-01-04T12:51:44.682Z","version":"0.0.3"},{"reproduced":false,"score":1,"timestamp":"2026-01-04T12:51:44.468Z","version":"0.0.2"},{"reproduced":false,"score":1,"timestamp":"2026-01-04T12:51:57.879Z","version":"0.0.1"}]}