{"name":"jsx-loader","versions":[{"reproduced":false,"score":0.75,"timestamp":"2026-01-07T17:05:42.734Z","version":"0.13.2"},{"reproduced":false,"score":0.75,"timestamp":"2026-01-07T17:05:48.458Z","version":"0.13.1"},{"reproduced":false,"score":0.75,"timestamp":"2026-01-07T17:05:48.433Z","version":"0.12.2"},{"reproduced":false,"score":0.75,"timestamp":"2026-01-07T17:05:35.556Z","version":"0.12.1"},{"reproduced":false,"score":0.75,"timestamp":"2026-01-07T17:05:42.504Z","version":"0.12.0"},{"reproduced":false,"score":0.75,"timestamp":"2026-01-07T17:05:46.164Z","version":"0.11.2"},{"reproduced":false,"score":0,"timestamp":"2026-01-07T17:05:36.372Z","version":"0.11.0"}]}