{"name":"react-textarea-autosize","versions":[{"reproduced":false,"score":0.6363636363636364,"timestamp":"2026-01-09T10:32:18.314Z","version":"8.5.9"},{"reproduced":false,"score":0.7575757575757576,"timestamp":"2026-01-09T10:32:08.988Z","version":"8.5.8"},{"reproduced":false,"score":0.7575757575757576,"timestamp":"2026-01-09T10:32:02.657Z","version":"8.5.7"},{"reproduced":false,"score":0.7575757575757576,"timestamp":"2026-01-09T10:31:15.774Z","version":"8.5.6"},{"reproduced":false,"score":0.7575757575757576,"timestamp":"2026-01-09T10:05:02.660Z","version":"8.5.5"},{"reproduced":false,"score":0.7575757575757576,"timestamp":"2026-01-09T10:05:45.720Z","version":"8.5.4"},{"reproduced":false,"score":0.8787878787878788,"timestamp":"2026-01-09T10:04:54.120Z","version":"8.5.3"},{"reproduced":false,"score":0.84,"timestamp":"2026-01-09T10:04:51.078Z","version":"8.5.2"},{"reproduced":false,"score":0.6,"timestamp":"2026-01-09T10:04:21.561Z","version":"8.5.1"},{"reproduced":false,"score":0.6,"timestamp":"2026-01-09T10:04:19.254Z","version":"8.5.0"},{"reproduced":false,"score":0.3125,"timestamp":"2026-01-09T10:04:37.199Z","version":"8.4.1"},{"reproduced":false,"score":0.29411764705882354,"timestamp":"2026-01-09T10:02:56.333Z","version":"8.3.4"},{"reproduced":false,"score":0.29411764705882354,"timestamp":"2026-01-09T10:02:55.524Z","version":"8.3.3"},{"reproduced":false,"score":0.29411764705882354,"timestamp":"2026-01-09T10:02:44.269Z","version":"8.3.2"},{"reproduced":false,"score":0.5882352941176471,"timestamp":"2026-01-09T10:03:07.107Z","version":"8.3.1"},{"reproduced":false,"score":0.5882352941176471,"timestamp":"2026-01-09T10:01:53.286Z","version":"8.3.0"},{"reproduced":false,"score":0.5882352941176471,"timestamp":"2026-01-09T10:02:01.817Z","version":"8.2.0"},{"reproduced":false,"score":0.5882352941176471,"timestamp":"2026-01-09T09:58:31.646Z","version":"8.1.1"},{"reproduced":false,"score":0.5882352941176471,"timestamp":"2026-01-09T09:58:33.259Z","version":"8.1.0"},{"reproduced":false,"score":0.5294117647058824,"timestamp":"2026-01-09T09:58:26.687Z","version":"8.0.1"},{"reproduced":false,"score":0.5294117647058824,"timestamp":"2026-01-09T09:56:12.142Z","version":"8.0.0"},{"reproduced":false,"score":0.3333333333333333,"timestamp":"2026-01-09T09:57:58.046Z","version":"7.1.2"},{"reproduced":false,"score":0.3333333333333333,"timestamp":"2026-01-09T09:58:18.553Z","version":"7.1.1"},{"reproduced":false,"score":1,"timestamp":"2026-01-09T08:46:54.022Z","version":"5.0.7"},{"reproduced":false,"score":0.38461538461538464,"timestamp":"2026-01-09T08:46:01.235Z","version":"5.0.6"},{"reproduced":false,"score":0.38461538461538464,"timestamp":"2026-01-09T08:45:53.965Z","version":"5.0.5"},{"reproduced":false,"score":0.38461538461538464,"timestamp":"2026-01-09T08:45:57.674Z","version":"5.0.4"},{"reproduced":false,"score":0.45454545454545453,"timestamp":"2026-01-09T08:46:04.059Z","version":"5.0.3"},{"reproduced":false,"score":0.45454545454545453,"timestamp":"2026-01-09T08:45:51.074Z","version":"5.0.2"},{"reproduced":false,"score":0.45454545454545453,"timestamp":"2026-01-09T08:45:37.626Z","version":"5.0.1"},{"reproduced":false,"score":0.45454545454545453,"timestamp":"2026-01-09T08:45:19.297Z","version":"5.0.0"},{"reproduced":false,"score":0.5555555555555556,"timestamp":"2026-01-09T08:45:20.132Z","version":"4.3.2"},{"reproduced":false,"score":0.5555555555555556,"timestamp":"2026-01-09T08:45:13.326Z","version":"4.3.1"},{"reproduced":false,"score":0.5555555555555556,"timestamp":"2026-01-09T08:44:56.626Z","version":"4.3.0"},{"reproduced":false,"score":0.375,"timestamp":"2026-01-09T08:44:49.233Z","version":"4.2.2"},{"reproduced":false,"score":0.375,"timestamp":"2026-01-09T08:44:48.256Z","version":"4.2.1"},{"reproduced":false,"score":0.375,"timestamp":"2026-01-09T08:45:07.846Z","version":"4.2.0"},{"reproduced":false,"score":0.5,"timestamp":"2026-01-09T08:37:06.635Z","version":"4.1.0"},{"reproduced":false,"score":0.5,"timestamp":"2026-01-09T08:36:34.470Z","version":"4.0.5"},{"reproduced":false,"score":0.5714285714285714,"timestamp":"2026-01-09T08:36:20.258Z","version":"4.0.4"},{"reproduced":false,"score":0.5714285714285714,"timestamp":"2026-01-09T08:35:48.557Z","version":"4.0.3"},{"reproduced":false,"score":0.5714285714285714,"timestamp":"2026-01-09T08:35:48.887Z","version":"4.0.2"},{"reproduced":false,"score":0.5714285714285714,"timestamp":"2026-01-09T08:35:26.225Z","version":"4.0.1"},{"reproduced":false,"score":0.5714285714285714,"timestamp":"2026-01-09T08:09:25.096Z","version":"4.0.0"},{"reproduced":false,"score":0.5714285714285714,"timestamp":"2026-01-09T08:09:18.057Z","version":"3.3.1"},{"reproduced":false,"score":0.5714285714285714,"timestamp":"2026-01-09T08:08:53.468Z","version":"3.3.0"},{"reproduced":false,"score":0.5714285714285714,"timestamp":"2026-01-09T08:08:46.318Z","version":"3.2.0"},{"reproduced":false,"score":0.5714285714285714,"timestamp":"2026-01-09T08:07:47.562Z","version":"3.1.0"},{"reproduced":false,"score":0.5714285714285714,"timestamp":"2026-01-09T08:08:09.982Z","version":"3.0.0"},{"reproduced":false,"score":0.5714285714285714,"timestamp":"2026-01-09T08:07:17.348Z","version":"2.5.4"},{"reproduced":false,"score":0.5714285714285714,"timestamp":"2026-01-09T08:07:15.916Z","version":"2.5.3"},{"reproduced":false,"score":0.5714285714285714,"timestamp":"2026-01-09T08:07:12.783Z","version":"2.5.2"},{"reproduced":false,"score":0.5714285714285714,"timestamp":"2026-01-09T08:06:54.652Z","version":"2.5.1"},{"reproduced":false,"score":0.5714285714285714,"timestamp":"2026-01-09T08:06:59.716Z","version":"2.5.0"},{"reproduced":false,"score":0.5714285714285714,"timestamp":"2026-01-09T08:06:49.915Z","version":"2.4.2"},{"reproduced":false,"score":0.5714285714285714,"timestamp":"2026-01-09T08:06:51.171Z","version":"2.4.1"},{"reproduced":false,"score":0.5714285714285714,"timestamp":"2026-01-09T08:07:18.777Z","version":"2.4.0"},{"reproduced":false,"score":0.5714285714285714,"timestamp":"2026-01-09T08:06:33.725Z","version":"2.3.1"},{"reproduced":false,"score":0.5714285714285714,"timestamp":"2026-01-09T08:06:18.117Z","version":"2.3.0"},{"reproduced":false,"score":0.5714285714285714,"timestamp":"2026-01-09T08:06:23.217Z","version":"2.2.3"},{"reproduced":false,"score":0.5714285714285714,"timestamp":"2026-01-09T08:06:16.144Z","version":"2.2.2"},{"reproduced":false,"score":0.5714285714285714,"timestamp":"2026-01-09T08:06:01.080Z","version":"2.2.1"},{"reproduced":false,"score":0.5714285714285714,"timestamp":"2026-01-09T08:05:47.473Z","version":"2.2.0"},{"reproduced":false,"score":0.5714285714285714,"timestamp":"2026-01-09T07:33:57.092Z","version":"2.1.3"},{"reproduced":false,"score":0.5714285714285714,"timestamp":"2026-01-09T07:35:23.870Z","version":"2.1.2"},{"reproduced":false,"score":0.5714285714285714,"timestamp":"2026-01-09T07:34:16.099Z","version":"2.1.1"},{"reproduced":false,"score":0.5714285714285714,"timestamp":"2026-01-09T07:36:01.392Z","version":"2.1.0"},{"reproduced":false,"score":0.5714285714285714,"timestamp":"2026-01-09T07:35:30.723Z","version":"2.0.1"},{"reproduced":false,"score":0.5714285714285714,"timestamp":"2026-01-09T07:35:41.277Z","version":"2.0.0"},{"reproduced":false,"score":0.9090909090909091,"timestamp":"2026-01-09T07:35:49.827Z","version":"1.1.0"},{"reproduced":false,"score":0.9090909090909091,"timestamp":"2026-01-09T07:35:16.145Z","version":"1.0.6"},{"reproduced":false,"score":0.9090909090909091,"timestamp":"2026-01-09T07:34:08.414Z","version":"1.0.5"},{"reproduced":false,"score":0.9090909090909091,"timestamp":"2026-01-09T07:35:25.583Z","version":"1.0.4"},{"reproduced":false,"score":0.8888888888888888,"timestamp":"2026-01-09T07:35:49.559Z","version":"1.0.3"},{"reproduced":false,"score":0.875,"timestamp":"2026-01-09T07:34:31.619Z","version":"1.0.2"},{"reproduced":false,"score":0.7142857142857143,"timestamp":"2026-01-09T07:35:09.661Z","version":"1.0.1"},{"reproduced":false,"score":0.7142857142857143,"timestamp":"2026-01-09T07:35:28.679Z","version":"1.0.0"},{"reproduced":false,"score":0.8333333333333334,"timestamp":"2026-01-09T07:33:46.753Z","version":"0.3.1"},{"reproduced":false,"score":0.8333333333333334,"timestamp":"2026-01-09T07:34:11.743Z","version":"0.3.0"},{"reproduced":false,"score":0.8333333333333334,"timestamp":"2026-01-09T07:34:46.759Z","version":"0.2.0"},{"reproduced":false,"score":0.8333333333333334,"timestamp":"2026-01-09T07:35:11.099Z","version":"0.1.2"},{"reproduced":false,"score":0.8333333333333334,"timestamp":"2026-01-09T07:35:19.420Z","version":"0.1.1"},{"reproduced":false,"score":0.8333333333333334,"timestamp":"2026-01-09T07:35:05.074Z","version":"0.1.0"}]}